doughnuts/Myplugin.py
doughnuts/__main__.py
doughnuts/auxiliary/av/av.json
doughnuts/auxiliary/fpm/ant_x64.dll
doughnuts/auxiliary/fpm/ant_x64.so
doughnuts/auxiliary/fpm/ant_x86.dll
doughnuts/auxiliary/fpm/ant_x86.so
doughnuts/auxiliary/fpm/fpm.py
doughnuts/auxiliary/iconv/iconv.c
doughnuts/auxiliary/iconv/iconv_x64.so
doughnuts/auxiliary/iconv/iconv_x86.so
doughnuts/auxiliary/ld_preload/ld_preload.c
doughnuts/auxiliary/ld_preload/ld_preload_x64.so
doughnuts/auxiliary/ld_preload/ld_preload_x86.so
doughnuts/auxiliary/neoreg/tunnel.php
doughnuts/auxiliary/neoreg/x.py
doughnuts/auxiliary/priv/gtfo.json
doughnuts/auxiliary/reshell/reverse_server_light.zip
doughnuts/auxiliary/reshell/reverse_server_x86_64
doughnuts/auxiliary/udf/README.txt
doughnuts/auxiliary/udf/mysql/linux/32/lib_mysqludf_sys.so
doughnuts/auxiliary/udf/mysql/linux/64/lib_mysqludf_sys.so
doughnuts/auxiliary/udf/mysql/windows/32/lib_mysqludf_sys.dll
doughnuts/auxiliary/udf/mysql/windows/64/lib_mysqludf_sys.dll
doughnuts/auxiliary/udf/postgresql/linux/32/8.2/lib_postgresqludf_sys.so
doughnuts/auxiliary/udf/postgresql/linux/32/8.3/lib_postgresqludf_sys.so
doughnuts/auxiliary/udf/postgresql/linux/32/8.4/lib_postgresqludf_sys.so
doughnuts/auxiliary/udf/postgresql/linux/32/9.0/lib_postgresqludf_sys.so
doughnuts/auxiliary/udf/postgresql/linux/64/8.2/lib_postgresqludf_sys.so
doughnuts/auxiliary/udf/postgresql/linux/64/8.3/lib_postgresqludf_sys.so
doughnuts/auxiliary/udf/postgresql/linux/64/8.4/lib_postgresqludf_sys.so
doughnuts/auxiliary/udf/postgresql/linux/64/9.0/lib_postgresqludf_sys.so
doughnuts/auxiliary/udf/postgresql/windows/32/8.2/lib_postgresqludf_sys.dll
doughnuts/auxiliary/udf/postgresql/windows/32/8.3/lib_postgresqludf_sys.dll
doughnuts/auxiliary/udf/postgresql/windows/32/8.4/lib_postgresqludf_sys.dll
doughnuts/auxiliary/udf/postgresql/windows/32/9.0/lib_postgresqludf_sys.dll
doughnuts/auxiliary/user_agents/ua.txt
doughnuts/auxiliary/zip/zip.php
doughnuts/config.ini
doughnuts-4.24.2.dist-info/LICENSE
doughnuts-4.24.2.dist-info/METADATA
doughnuts-4.24.2.dist-info/WHEEL
doughnuts-4.24.2.dist-info/RECORD
