Metadata-Version: 2.1
Name: doughnuts
Version: 4.24.2
Summary: A webshell manager for PHP
Home-page: https://github.com/way29/doughnuts
License: MIT
Author: WAY29
Author-email: toloveu29@gmail.com
Requires-Python: >=3.6,<4.0
Classifier: License :: OSI Approved :: MIT License
Classifier: Programming Language :: Python :: 3
Classifier: Programming Language :: Python :: 3.6
Classifier: Programming Language :: Python :: 3.7
Classifier: Programming Language :: Python :: 3.8
Classifier: Programming Language :: Python :: 3.9
Classifier: Programming Language :: Python :: 3.10
Classifier: Programming Language :: Python :: 3.11
Requires-Dist: colorama (>=0.4.3,<0.5.0)
Requires-Dist: prettytable (>=0.7.2,<0.8.0)
Requires-Dist: pysocks (>=1.7.1,<2.0.0)
Requires-Dist: requests (>=2.23.0,<3.0.0)
Requires-Dist: six (>=1.15.0,<2.0.0)
Requires-Dist: tqdm (>=4.50.2,<5.0.0)
Project-URL: Repository, https://github.com/way29/doughnuts
